aslabs/dependencies/gcp/storage/__init__.py
aslabs/dependencies/gcp/storage/storage.py
aslabs_dependencies_gcp_storage-0.0.1.dist-info/WHEEL
aslabs_dependencies_gcp_storage-0.0.1.dist-info/METADATA
aslabs_dependencies_gcp_storage-0.0.1.dist-info/RECORD
