Metadata-Version: 2.1
Name: aslabs-dependencies-gcp-storage
Version: 0.0.1
Summary: 
Author: Titusz Ban
Author-email: tituszban@antisociallabs.io
Requires-Python: >=3.9,<4.0
Classifier: Programming Language :: Python :: 3
Classifier: Programming Language :: Python :: 3.9
Classifier: Programming Language :: Python :: 3.10
Classifier: Programming Language :: Python :: 3.11
Requires-Dist: aslabs-dependencies (>=0.0.3,<0.0.4)
Requires-Dist: google-cloud-storage (>=2.4.0,<3.0.0)
